easyISA/__init__.py
easyISA/equations.py
easyISA-0.1.1.dist-info/METADATA
easyISA-0.1.1.dist-info/WHEEL
easyISA-0.1.1.dist-info/top_level.txt
easyISA-0.1.1.dist-info/RECORD
