Metadata-Version: 2.1
Name: easyISA
Version: 0.1.1
Summary: Easy implementation of ISA equations
Home-page: https://github.com/jaimebw/easyISA
Author: Jaime Bowen
Author-email: jaimebwv@gmail.com
License: MIT
Platform: UNKNOWN
Requires-Python: >=3.6
